iree/turbine/__init__.py
iree/turbine/py.typed
iree/turbine/aot/__init__.py
iree/turbine/aot/build_actions.py
iree/turbine/aot/compiled_module.py
iree/turbine/aot/decompositions.py
iree/turbine/aot/exporter.py
iree/turbine/aot/fx_programs.py
iree/turbine/aot/params.py
iree/turbine/aot/tensor_traits.py
iree/turbine/aot/builtins/__init__.py
iree/turbine/aot/builtins/globals.py
iree/turbine/aot/builtins/jittable.py
iree/turbine/aot/passes/__init__.py
iree/turbine/aot/passes/functorch.py
iree/turbine/aot/support/ir_utils.py
iree/turbine/aot/support/procedural/__init__.py
iree/turbine/aot/support/procedural/base.py
iree/turbine/aot/support/procedural/exported_program.py
iree/turbine/aot/support/procedural/globals.py
iree/turbine/aot/support/procedural/iree_emitter.py
iree/turbine/aot/support/procedural/primitives.py
iree/turbine/aot/support/procedural/tracer.py
iree/turbine/aot/testing/example_builder.py
iree/turbine/dynamo/__init__.py
iree/turbine/dynamo/decompositions.py
iree/turbine/dynamo/executor.py
iree/turbine/dynamo/passes.py
iree/turbine/dynamo/tensor.py
iree/turbine/dynamo/type_conversion.py
iree/turbine/dynamo/backends/base.py
iree/turbine/dynamo/backends/boo.py
iree/turbine/importers/ir.py
iree/turbine/importers/utils.py
iree/turbine/kernel/__init__.py
iree/turbine/kernel/_support/context.py
iree/turbine/kernel/_support/dtype.py
iree/turbine/kernel/_support/indexing.py
iree/turbine/kernel/_support/location.py
iree/turbine/kernel/_support/location_config.py
iree/turbine/kernel/_support/regions.py
iree/turbine/kernel/_support/shaped_type.py
iree/turbine/kernel/_support/tracing.py
iree/turbine/kernel/boo/__init__.py
iree/turbine/kernel/boo/driver/driver.py
iree/turbine/kernel/boo/driver/launch.py
iree/turbine/kernel/boo/driver/numerics.py
iree/turbine/kernel/boo/driver/utils.py
iree/turbine/kernel/boo/examples/conv_launchable.py
iree/turbine/kernel/boo/examples/resnet_18_backward.py
iree/turbine/kernel/boo/examples/subgraph_extraction.py
iree_turbine-3.8.0.dist-info/licenses/LICENSE
iree_turbine-3.8.0.dist-info/METADATA
iree_turbine-3.8.0.dist-info/WHEEL
iree_turbine-3.8.0.dist-info/entry_points.txt
iree_turbine-3.8.0.dist-info/top_level.txt
iree_turbine-3.8.0.dist-info/RECORD
