Metadata-Version: 2.4
Name: iree-turbine
Version: 3.8.0
Summary: IREE Turbine Machine Learning Deployment Tools
Author: IREE Authors
Author-email: iree-technical-discussion@lists.lfaidata.foundation
License: Apache-2.0
Project-URL: homepage, https://iree.dev/
Project-URL: repository, https://github.com/iree-org/iree-turbine/
Project-URL: documentation, https://iree-turbine.readthedocs.io/en/latest/
Classifier: Development Status :: 5 - Production/Stable
Classifier: License :: OSI Approved :: Apache Software License
Classifier: Programming Language :: Python :: 3
License-File: LICENSE
Requires-Dist: numpy
Requires-Dist: iree-base-compiler
Requires-Dist: iree-base-runtime
Requires-Dist: Jinja2>=3.1.4
Requires-Dist: ml_dtypes>=0.5.0
Requires-Dist: typing_extensions
Provides-Extra: testing
Requires-Dist: pytest>=8.0.0; extra == "testing"
Requires-Dist: pytest-xdist>=3.5.0; extra == "testing"
Requires-Dist: parameterized>=0.9.0; extra == "testing"
Dynamic: author
Dynamic: author-email
Dynamic: classifier
Dynamic: description
Dynamic: description-content-type
Dynamic: license
Dynamic: license-file
Dynamic: project-url
Dynamic: provides-extra
Dynamic: requires-dist
Dynamic: summary
